{
  "issues": [
    {
      "id": "1",
      "titulo": "Error en el login",
      "descripcion": "El botón de login no responde al hacer clic.",
      "estado": "Pendiente",
      "prioridad": "Alta"
    },
    {
      "id": "2",
      "titulo": "Faltan iconos en el sidebar",
      "descripcion": "Los iconos de configuración no se visualizan.",
      "estado": "En Progreso",
      "prioridad": "Media"
    },
    {
      "titulo": "falta crear un modelo hamburguesa",
      "descripcion": "para que se ve mejor desde el celular",
      "estado": "Pendiente",
      "prioridad": "Media",
      "id": "iAkPgqXhvOw"
    }
  ],
  "$schema": "./node_modules/json-server/schema.json"
}